wasmpy/util.py
wasmpy/nativelib.abi3.so
wasmpy/spectest.abi3.so
wasmpy/opcodes.json
wasmpy/native.py
wasmpy/__init__.py
wasmpy/binary/values.py
wasmpy/binary/types.py
wasmpy/binary/sections.py
wasmpy/binary/module.py
wasmpy/binary/instructions.py
wasmpy/binary/__init__.py
wasmpy/text/sections.py
wasmpy/text/module.py
wasmpy/text/instructions.py
wasmpy/text/__init__.py
wasmpy-0.2.3.dist-info/WHEEL
wasmpy-0.2.3.dist-info/METADATA
wasmpy-0.2.3.dist-info/RECORD
wasmpy-0.2.3.dist-info/top_level.txt
wasmpy-0.2.3.dist-info/LICENSE
