Metadata-Version: 2.1
Name: wasmpy
Version: 0.2.3
Summary: WebAssembly in Python.
Home-page: https://github.com/olivi-r/wasmpy
Author: Olivia Ryan
Author-email: olivia.r.dev@gmail.com
License: MIT
Classifier: Development Status :: 3 - Alpha
Classifier: Intended Audience :: Developers
Classifier: Environment :: WebAssembly
Classifier: Programming Language :: C++
Classifier: Programming Language :: Assembly
Classifier: Programming Language :: Python :: 3.6
Classifier: Programming Language :: Python :: 3.7
Classifier: Programming Language :: Python :: 3.8
Classifier: Programming Language :: Python :: 3.9
Classifier: Programming Language :: Python :: 3.10
Classifier: Programming Language :: Python :: 3.11
Classifier: License :: OSI Approved :: MIT License
Requires-Python: >=3.6
License-File: LICENSE
